django_chilies/__init__.py
django_chilies/celery.py
django_chilies/common.py
django_chilies/controllers.py
django_chilies/errors.py
django_chilies/middlewares.py
django_chilies/models.py
django_chilies/serializers.py
django_chilies/settings.py
django_chilies/trackers.py
django_chilies/utils.py
django_chilies/writers.py
django_chilies/models/__init__.py
django_chilies/models/compositefk/__init__.py
django_chilies/models/compositefk/compat.py
django_chilies/models/compositefk/fields.py
django_chilies/models/compositefk/related_descriptors.py
django_chilies-0.0.2a1.dist-info/LICENSE
django_chilies-0.0.2a1.dist-info/METADATA
django_chilies-0.0.2a1.dist-info/WHEEL
django_chilies-0.0.2a1.dist-info/top_level.txt
django_chilies-0.0.2a1.dist-info/RECORD
